{
    "name": "MicrosoftCloudAppSecurity.AustraliaEast",
    "id": "MicrosoftCloudAppSecurity.AustraliaEast",
    "properties": {
        "changeNumber": 3,
        "region": "australiaeast",
        "regionId": 3,
        "platform": "Azure",
        "systemService": "MicrosoftCloudAppSecurity",
        "addressPrefixes": [
            "13.70.74.160/27",
            "20.227.120.240/28",
            "20.227.121.128/25",
            "20.227.125.0/29",
            "68.218.141.6/31",
            "68.218.141.8/29",
            "68.218.141.16/28",
            "68.218.141.32/30"
        ],
        "networkFeatures": null
    }
}