{
    "name": "PowerQueryOnline.SwedenCentral",
    "id": "PowerQueryOnline.SwedenCentral",
    "properties": {
        "changeNumber": 8,
        "region": "swedencentral",
        "regionId": 76,
        "platform": "Azure",
        "systemService": "PowerQueryOnline",
        "addressPrefixes": [
            "51.12.33.50/31",
            "51.12.46.228/31",
            "51.12.75.224/29",
            "51.12.229.244/31",
            "51.12.238.168/31",
            "135.225.43.0/28",
            "135.225.43.16/29",
            "2603:1020:1004::200/123",
            "2603:1020:1004:402::20/125",
            "2603:1020:1004:800::460/125",
            "2603:1020:1004:c00::/125"
        ],
        "networkFeatures": null
    }
}